gruel/__init__.py
gruel/brewer.py
gruel/core.py
gruel/crawler.py
gruel/models.py
gruel/py.typed
gruel/requests.py
gruel/subgruel.py
gruel/template.py
gruel-4.6.0.dist-info/METADATA
gruel-4.6.0.dist-info/WHEEL
gruel-4.6.0.dist-info/entry_points.txt
gruel-4.6.0.dist-info/licenses/LICENSE.txt
gruel-4.6.0.dist-info/RECORD
